jupyterlab_launchpad/__init__.py
jupyterlab_launchpad/_version.py
jupyterlab_launchpad/handlers.py
jupyterlab_launchpad-1.0.2.data/data/etc/jupyter/jupyter_server_config.d/jupyterlab_new_launcher.json
jupyterlab_launchpad-1.0.2.data/data/share/jupyter/labextensions/jupyterlab-launchpad/package.json
jupyterlab_launchpad-1.0.2.data/data/share/jupyter/labextensions/jupyterlab-launchpad/schemas/jupyterlab-launchpad/package.json.orig
jupyterlab_launchpad-1.0.2.data/data/share/jupyter/labextensions/jupyterlab-launchpad/schemas/jupyterlab-launchpad/plugin.json
jupyterlab_launchpad-1.0.2.data/data/share/jupyter/labextensions/jupyterlab-launchpad/static/728.9178385d8d4d0ac5d8a8.js
jupyterlab_launchpad-1.0.2.data/data/share/jupyter/labextensions/jupyterlab-launchpad/static/930.544295ea2fbd4c4f0c04.js
jupyterlab_launchpad-1.0.2.data/data/share/jupyter/labextensions/jupyterlab-launchpad/static/remoteEntry.0a33f1c4baa38d86e85a.js
jupyterlab_launchpad-1.0.2.data/data/share/jupyter/labextensions/jupyterlab-launchpad/static/style.js
jupyterlab_launchpad-1.0.2.data/data/share/jupyter/labextensions/jupyterlab-launchpad/static/third-party-licenses.json
jupyterlab_launchpad-1.0.2.data/data/share/jupyter/labextensions/jupyterlab-launchpad/install.json
jupyterlab_launchpad-1.0.2.dist-info/METADATA
jupyterlab_launchpad-1.0.2.dist-info/WHEEL
jupyterlab_launchpad-1.0.2.dist-info/licenses/LICENSE
jupyterlab_launchpad-1.0.2.dist-info/RECORD
